automation_utilities/Authintication.py
automation_utilities/Data.py
automation_utilities/Exceptions.py
automation_utilities/Files.py
automation_utilities/FiveSim.py
automation_utilities/Generator.py
automation_utilities/Input.py
automation_utilities/Intro.py
automation_utilities/MailTM.py
automation_utilities/Mediafire.py
automation_utilities/MediafireTest.py
automation_utilities/PhoneNumbers.py
automation_utilities/Premiumy.py
automation_utilities/Print.py
automation_utilities/Proxy.py
automation_utilities/URLs.py
automation_utilities/Update.py
automation_utilities/__init__.py
automation_utilities/email_fake.py
automation_utilities/test.py
automation_utilities-1.5.8.dist-info/METADATA
automation_utilities-1.5.8.dist-info/WHEEL
automation_utilities-1.5.8.dist-info/top_level.txt
automation_utilities-1.5.8.dist-info/RECORD
